<?xml version="1.0"?>
<!-- file "D:\Programming\solarus\sample_quest/data/sprites/entities/bomb.xml", generated by LuaXML -->

<Sprite>
  <Animation Name="stopped">
    <SrcImage>entities/bomb.png</SrcImage>
    <Direction>
      <X>0</X>
      <Y>0</Y>
      <FrameWidth>16</FrameWidth>
      <FrameHeight>16</FrameHeight>
      <OriginX>8</OriginX>
      <OriginY>13</OriginY>
    </Direction>
  </Animation>
  <Animation Name="stopped_explosion_soon">
    <SrcImage>entities/bomb.png</SrcImage>
    <FrameDelay>50</FrameDelay>
    <FrameToLoopOn>0</FrameToLoopOn>
    <Direction>
      <X>0</X>
      <Y>0</Y>
      <FrameWidth>16</FrameWidth>
      <FrameHeight>16</FrameHeight>
      <OriginX>8</OriginX>
      <OriginY>13</OriginY>
      <NumFrames>4</NumFrames>
    </Direction>
  </Animation>
  <Animation Name="walking">
    <SrcImage>entities/bomb.png</SrcImage>
    <FrameDelay>100</FrameDelay>
    <FrameToLoopOn>0</FrameToLoopOn>
    <Direction>
      <X>0</X>
      <Y>16</Y>
      <FrameWidth>16</FrameWidth>
      <FrameHeight>24</FrameHeight>
      <OriginX>8</OriginX>
      <OriginY>13</OriginY>
      <NumFrames>3</NumFrames>
    </Direction>
  </Animation>
  <Animation Name="walking_explosion_soon">
    <SrcImage>entities/bomb.png</SrcImage>
    <FrameDelay>50</FrameDelay>
    <FrameToLoopOn>0</FrameToLoopOn>
    <Direction>
      <X>48</X>
      <Y>16</Y>
      <FrameWidth>16</FrameWidth>
      <FrameHeight>24</FrameHeight>
      <OriginX>8</OriginX>
      <OriginY>13</OriginY>
      <NumFrames>3</NumFrames>
    </Direction>
  </Animation>
</Sprite>
